modelsocket-0.2.1.dist-info/METADATA
modelsocket-0.2.1.dist-info/WHEEL
modelsocket/__init__.py
modelsocket/modelsocket.abi3.so
modelsocket-0.2.1.dist-info/RECORD
