Metadata-Version: 2.4
Name: modelsocket
Version: 0.2.1
Summary: A Rust library for ModelSocket, a protocol for efficiently integrating with LLMs
Keywords: modelsocket,ai,llm
License: Apache-2.0
